pyscigraph/VERSION.py
pyscigraph/__init__.py
pyscigraph/lib.py
pyscigraph/main.py
pyscigraph/utils.py
pyscigraph/tests/__init__.py
pyscigraph/tests/quicktest.py
pyscigraph/tests/test_one.py
pyscigraph-0.6.dist-info/LICENSE
pyscigraph-0.6.dist-info/METADATA
pyscigraph-0.6.dist-info/WHEEL
pyscigraph-0.6.dist-info/entry_points.txt
pyscigraph-0.6.dist-info/top_level.txt
pyscigraph-0.6.dist-info/RECORD
