Metadata-Version: 2.1
Name: pyscigraph
Version: 0.6
Summary: Python API for accessing Springer Nature SciGraph Linked Open Data.
Home-page: https://github.com/lambdamusic/pyscigraph
License: UNKNOWN
Platform: UNKNOWN
License-File: LICENSE
Requires-Dist: Click
Requires-Dist: Requests
Requires-Dist: rdflib
Requires-Dist: rdflib-jsonld
Requires-Dist: ontospy
